vitables/LICENSE.html
vitables/__init__.py
vitables/__main__.py
vitables/filenodeutils.py
vitables/logger.py
vitables/start.py
vitables/utils.py
vitables/vtapp.py
vitables/vtgui.py
vitables/vtsite.py
vitables/vtsplash.py
vitables/calculator/__init__.py
vitables/calculator/calculator.py
vitables/calculator/calculator.ui
vitables/calculator/calculator_dlg.py
vitables/calculator/evaluator.py
vitables/docbrowser/__init__.py
vitables/docbrowser/bookmarksdlg.py
vitables/docbrowser/browsergui.py
vitables/docbrowser/helpbrowser.py
vitables/extensions/__init__.py
vitables/extensions/about_page.ui
vitables/extensions/aboutpage.py
vitables/extensions/columnorg/__init__.py
vitables/extensions/columnorg/columnar_org.py
vitables/extensions/columnorg/icons/object-group.png
vitables/extensions/columnorg/icons/object-ungroup.png
vitables/extensions/dbstreesort/__init__.py
vitables/extensions/dbstreesort/aboutpage.py
vitables/extensions/dbstreesort/dbs_tree_sort.py
vitables/extensions/dbstreesort/dbs_tree_sort_page.ui
vitables/extensions/dbstreesort/sorting_algorithm.ini
vitables/extensions/timeseries/__init__.py
vitables/extensions/timeseries/aboutpage.py
vitables/extensions/timeseries/time_format.ini
vitables/extensions/timeseries/time_series.py
vitables/extensions/timeseries/timeformatter_page.ui
vitables/h5db/__init__.py
vitables/h5db/dbdoc.py
vitables/h5db/dbstreemodel.py
vitables/h5db/dbstreeview.py
vitables/h5db/groupnode.py
vitables/h5db/leafnode.py
vitables/h5db/linknode.py
vitables/h5db/nodeitemdelegate.py
vitables/h5db/rootgroupnode.py
vitables/h5db/tlink_editor.py
vitables/h5db/tnode_editor.py
vitables/htmldocs/.buildinfo
vitables/htmldocs/develop.html
vitables/htmldocs/genindex.html
vitables/htmldocs/index.html
vitables/htmldocs/objects.inv
vitables/htmldocs/search.html
vitables/htmldocs/searchindex.js
vitables/htmldocs/usersguide-app1.html
vitables/htmldocs/usersguide-app2.html
vitables/htmldocs/usersguide-ch1.html
vitables/htmldocs/usersguide-ch2.html
vitables-3.1.0.dist-info/METADATA
vitables-3.1.0.dist-info/WHEEL
vitables-3.1.0.dist-info/entry_points.txt
vitables-3.1.0.dist-info/licenses/LICENSE.txt
vitables-3.1.0.dist-info/RECORD
