Metadata-Version: 2.4
Name: ViTables
Version: 3.1.0
Summary: A viewer for HDF5 files.
Project-URL: Documentation, https://github.com/uvemas/ViTables#readme
Project-URL: Issues, https://github.com/uvemas/ViTables/issues
Project-URL: Source, https://github.com/uvemas/ViTables
Project-URL: Home, https://vitables.org
Author-email: Vicent Mas <vmas@vitables.org>
License-File: LICENSE.txt
Keywords: HDF5,PyTables
Classifier: Development Status :: 5 - Production/Stable
Classifier: Environment :: MacOS X
Classifier: Environment :: Win32 (MS Windows)
Classifier: Environment :: X11 Applications
Classifier: License :: OSI Approved :: GNU General Public License v3 or later (GPLv3+)
Classifier: Operating System :: POSIX
Classifier: Programming Language :: Python
Classifier: Topic :: Scientific/Engineering
Requires-Python: >=3.10
Requires-Dist: numpy>=2.0
Requires-Dist: qtpy>=2.2
Requires-Dist: tables>=3.0
Provides-Extra: pyqt6
Requires-Dist: pyqt6>=6.0; extra == 'pyqt6'
Provides-Extra: pyside6
Requires-Dist: pyside6>=6.4; extra == 'pyside6'
